{
  "lstm": {
    "588": {
      "patient_id": "588",
      "strategy": "periodic",
      "retraining_interval_days": 7,
      "summary": {
        "mae_mean": 29.832881988866127,
        "mae_std": 8.551061679389916,
        "rmse_mean": 36.65015725755021,
        "rmse_std": 10.895996308405437,
        "clarke_ab_mean": 97.2143937490665,
        "clarke_ab_std": 2.8958992065660176,
        "total_days_evaluated": 39,
        "total_retrains": 5
      },
      "sawtooth_pattern": {
        "0": {
          "mae_mean": 31.984116445325697,
          "mae_std": 13.696075502875004,
          "rmse_mean": 42.11811195065358,
          "rmse_std": 20.20315311640118,
          "n_samples": 6
        },
        "1": {
          "mae_mean": 29.955587194970747,
          "mae_std": 5.9697358488367716,
          "rmse_mean": 36.83349391788005,
          "rmse_std": 6.469274621410665,
          "n_samples": 6
        },
        "2": {
          "mae_mean": 28.264903814297934,
          "mae_std": 6.2221186240645086,
          "rmse_mean": 34.48417199949294,
          "rmse_std": 5.978545145038292,
          "n_samples": 6
        },
        "3": {
          "mae_mean": 28.592970917848575,
          "mae_std": 3.810637763410499,
          "rmse_mean": 34.65161313700595,
          "rmse_std": 4.135070507729925,
          "n_samples": 6
        },
        "4": {
          "mae_mean": 29.03548549596959,
          "mae_std": 6.420165803822519,
          "rmse_mean": 35.41262684396216,
          "rmse_std": 6.365066920730396,
          "n_samples": 5
        },
        "5": {
          "mae_mean": 32.88488575519168,
          "mae_std": 7.5682881928125925,
          "rmse_mean": 38.93932288936787,
          "rmse_std": 9.378009459986343,
          "n_samples": 5
        },
        "6": {
          "mae_mean": 28.219014215062977,
          "mae_std": 10.824729135109532,
          "rmse_mean": 33.81440766952267,
          "rmse_std": 11.532073723561455,
          "n_samples": 5
        }
      },
      "daily_metrics": [
        {
          "mae": 60.16112942148042,
          "rmse": 85.04241778978529,
          "mse": 7232.212823532391,
          "mape": 35.04157607147124,
          "correlation": 0.8244701959323231,
          "r_squared": -16.04698868976637,
          "clarke_a": 43.05555555555556,
          "clarke_b": 53.125,
          "clarke_ab": 96.18055555555556,
          "day": 7,
          "days_since_retrain": 0
        },
        {
          "mae": 31.72146004238754,
          "rmse": 40.145866923725464,
          "mse": 1611.690631057474,
          "mape": 19.194151700546655,
          "correlation": 0.7467366685730645,
          "r_squared": -9.330959566384449,
          "clarke_a": 67.36111111111111,
          "clarke_b": 22.22222222222222,
          "clarke_ab": 89.58333333333334,
          "day": 8,
          "days_since_retrain": 1
        },
        {
          "mae": 25.103373132831766,
          "rmse": 29.499646119485767,
          "mse": 870.2291211748917,
          "mape": 16.247921921774065,
          "correlation": 0.829949913605297,
          "r_squared": -8.654041255834596,
          "clarke_a": 61.458333333333336,
          "clarke_b": 38.54166666666667,
          "clarke_ab": 100.0,
          "day": 9,
          "days_since_retrain": 2
        },
        {
          "mae": 29.842574976523938,
          "rmse": 37.052569387817414,
          "mse": 1372.892898239024,
          "mape": 19.2414755617338,
          "correlation": 0.7053159525516624,
          "r_squared": -3.1556094758035895,
          "clarke_a": 58.333333333333336,
          "clarke_b": 36.11111111111111,
          "clarke_ab": 94.44444444444444,
          "day": 10,
          "days_since_retrain": 3
        },
        {
          "mae": 27.776222837322614,
          "rmse": 39.66150212422102,
          "mse": 1573.0347507495885,
          "mape": 17.45661491934074,
          "correlation": 0.8229606230514368,
          "r_squared": -13.653781120992418,
          "clarke_a": 69.77611940298507,
          "clarke_b": 23.134328358208954,
          "clarke_ab": 92.91044776119404,
          "day": 11,
          "days_since_retrain": 4
        },
        {
          "mae": 37.24755570280724,
          "rmse": 42.33952360300086,
          "mse": 1792.635258929067,
          "mape": 23.70934209529069,
          "correlation": 0.916513908030827,
          "r_squared": -11.034498171636121,
          "clarke_a": 47.76119402985074,
          "clarke_b": 45.8955223880597,
          "clarke_ab": 93.65671641791045,
          "day": 12,
          "days_since_retrain": 5
        },
        {
          "mae": 21.358271618452257,
          "rmse": 26.81091716109095,
          "mse": 718.8252790188811,
          "mape": 14.212186287871113,
          "correlation": 0.7313182517812763,
          "r_squared": -7.844663027875365,
          "clarke_a": 73.61111111111111,
          "clarke_b": 26.38888888888889,
          "clarke_ab": 100.0,
          "day": 13,
          "days_since_retrain": 6
        },
        {
          "mae": 22.49279016838072,
          "rmse": 26.068499750792526,
          "mse": 679.5666792570701,
          "mape": 13.352906198448004,
          "correlation": 0.6662281015899802,
          "r_squared": -4.244725064249716,
          "clarke_a": 65.97222222222221,
          "clarke_b": 32.98611111111111,
          "clarke_ab": 98.95833333333331,
          "day": 14,
          "days_since_retrain": 0
        },
        {
          "mae": 24.50451777753117,
          "rmse": 28.65399017252169,
          "mse": 821.0511528069696,
          "mape": 15.031264602099675,
          "correlation": 0.818896842658585,
          "r_squared": -3.0873414542869044,
          "clarke_a": 62.15277777777778,
          "clarke_b": 37.15277777777778,
          "clarke_ab": 99.30555555555556,
          "day": 15,
          "days_since_retrain": 1
        },
        {
          "mae": 26.05092562824491,
          "rmse": 33.137705551683155,
          "mse": 1098.1075292300527,
          "mape": 16.58740037608016,
          "correlation": 0.7127873695047026,
          "r_squared": -1.3418004075363026,
          "clarke_a": 58.68055555555556,
          "clarke_b": 39.93055555555556,
          "clarke_ab": 98.61111111111111,
          "day": 16,
          "days_since_retrain": 2
        },
        {
          "mae": 33.097389200847815,
          "rmse": 38.8460405106397,
          "mse": 1509.014863354261,
          "mape": 20.80777530848693,
          "correlation": 0.6558486711385867,
          "r_squared": -3.242910273850624,
          "clarke_a": 50.0,
          "clarke_b": 46.52777777777778,
          "clarke_ab": 96.52777777777777,
          "day": 17,
          "days_since_retrain": 3
        },
        {
          "mae": 26.871264769306485,
          "rmse": 31.104712421487413,
          "mse": 967.5031348234334,
          "mape": 15.347087853892075,
          "correlation": 0.780919273247699,
          "r_squared": -3.4186029851794437,
          "clarke_a": 60.747663551401864,
          "clarke_b": 35.981308411214954,
          "clarke_ab": 96.72897196261681,
          "day": 18,
          "days_since_retrain": 4
        },
        {
          "mae": 28.67490597002276,
          "rmse": 34.82645346236441,
          "mse": 1212.8818607662342,
          "mape": 15.558207496811328,
          "correlation": 0.7699484951012192,
          "r_squared": -1.2063721748065288,
          "clarke_a": 74.65277777777779,
          "clarke_b": 19.791666666666664,
          "clarke_ab": 94.44444444444446,
          "day": 19,
          "days_since_retrain": 5
        },
        {
          "mae": 24.714549157341594,
          "rmse": 28.934756419161147,
          "mse": 837.2201290361871,
          "mape": 14.782245574503461,
          "correlation": 0.7318595314280248,
          "r_squared": -2.829127890428882,
          "clarke_a": 60.763888888888886,
          "clarke_b": 38.88888888888889,
          "clarke_ab": 99.65277777777777,
          "day": 20,
          "days_since_retrain": 6
        },
        {
          "mae": 22.81360083977024,
          "rmse": 30.065568865110023,
          "mse": 903.9384311826733,
          "mape": 15.327596311226246,
          "correlation": 0.43532892688361835,
          "r_squared": -1.6163761448146108,
          "clarke_a": 64.23611111111111,
          "clarke_b": 34.375,
          "clarke_ab": 98.61111111111111,
          "day": 21,
          "days_since_retrain": 0
        },
        {
          "mae": 32.44607597816162,
          "rmse": 40.5738012350288,
          "mse": 1646.233346659625,
          "mape": 20.774760683278316,
          "correlation": 0.21687652403999946,
          "r_squared": -3.6886278691155736,
          "clarke_a": 53.84615384615385,
          "clarke_b": 38.46153846153847,
          "clarke_ab": 92.30769230769232,
          "day": 22,
          "days_since_retrain": 1
        },
        {
          "mae": 34.88177111471342,
          "rmse": 41.181547001115966,
          "mse": 1695.9198134051237,
          "mape": 21.72807182441877,
          "correlation": 0.7911357012925173,
          "r_squared": -2.105596785833018,
          "clarke_a": 57.291666666666664,
          "clarke_b": 39.58333333333333,
          "clarke_ab": 96.875,
          "day": 23,
          "days_since_retrain": 2
        },
        {
          "mae": 28.002706816601627,
          "rmse": 34.0139802979041,
          "mse": 1156.9508557062081,
          "mape": 18.395999930761167,
          "correlation": 0.7938080619845689,
          "r_squared": -4.165191497921992,
          "clarke_a": 53.47222222222222,
          "clarke_b": 46.52777777777778,
          "clarke_ab": 100.0,
          "day": 24,
          "days_since_retrain": 3
        },
        {
          "mae": 31.328171248703526,
          "rmse": 38.01130749318987,
          "mse": 1444.8594973418321,
          "mape": 18.423496253994067,
          "correlation": 0.8654195154800615,
          "r_squared": -1.2881957244373994,
          "clarke_a": 66.31944444444444,
          "clarke_b": 33.33333333333333,
          "clarke_ab": 99.65277777777777,
          "day": 25,
          "days_since_retrain": 4
        },
        {
          "mae": 26.84215409912841,
          "rmse": 33.9696201828931,
          "mse": 1153.9350953700184,
          "mape": 15.918927435502342,
          "correlation": 0.7298421846959726,
          "r_squared": -3.560216707233521,
          "clarke_a": 70.13888888888889,
          "clarke_b": 27.083333333333332,
          "clarke_ab": 97.22222222222221,
          "day": 26,
          "days_since_retrain": 5
        },
        {
          "mae": 25.506841091049957,
          "rmse": 31.64487976334448,
          "mse": 1001.3984152365291,
          "mape": 13.955265280318729,
          "correlation": 0.8247909473029318,
          "r_squared": -1.4171764512733454,
          "clarke_a": 80.20833333333334,
          "clarke_b": 19.444444444444446,
          "clarke_ab": 99.65277777777779,
          "day": 27,
          "days_since_retrain": 6
        },
        {
          "mae": 37.81714393591862,
          "rmse": 45.70089898055256,
          "mse": 2088.57216763067,
          "mape": 24.20241906349931,
          "correlation": 0.8271768087069471,
          "r_squared": -12.023713399108484,
          "clarke_a": 42.27642276422765,
          "clarke_b": 52.84552845528455,
          "clarke_ab": 95.1219512195122,
          "day": 28,
          "days_since_retrain": 0
        },
        {
          "mae": 40.26126786496569,
          "rmse": 47.277057292883356,
          "mse": 2235.1201462745753,
          "mape": 23.822454398170027,
          "correlation": 0.8552769661097912,
          "r_squared": -11.380932199531314,
          "clarke_a": 48.95833333333333,
          "clarke_b": 47.22222222222222,
          "clarke_ab": 96.18055555555554,
          "day": 29,
          "days_since_retrain": 1
        },
        {
          "mae": 25.580388891053175,
          "rmse": 30.992083957630463,
          "mse": 960.5092680368156,
          "mape": 15.575164510110206,
          "correlation": 0.7857667117502816,
          "r_squared": -5.1557997617534985,
          "clarke_a": 65.97222222222221,
          "clarke_b": 32.29166666666667,
          "clarke_ab": 98.26388888888889,
          "day": 30,
          "days_since_retrain": 2
        },
        {
          "mae": 26.400194314714945,
          "rmse": 33.153213572337066,
          "mse": 1099.1355701729944,
          "mape": 16.090583572107334,
          "correlation": 0.8125041446658807,
          "r_squared": -10.518487274757407,
          "clarke_a": 65.625,
          "clarke_b": 30.90277777777778,
          "clarke_ab": 96.52777777777777,
          "day": 31,
          "days_since_retrain": 3
        },
        {
          "mae": 39.447896329666044,
          "rmse": 42.97403720790476,
          "mse": 1846.7678739463825,
          "mape": 22.460484120221114,
          "correlation": 0.6473584309425522,
          "r_squared": -4.96007481085679,
          "clarke_a": 55.90277777777778,
          "clarke_b": 39.93055555555556,
          "clarke_ab": 95.83333333333334,
          "day": 32,
          "days_since_retrain": 4
        },
        {
          "mae": 45.7237735851612,
          "rmse": 55.389616392862365,
          "mse": 3068.009604148447,
          "mape": 25.480285930372325,
          "correlation": 0.660622692065453,
          "r_squared": -10.735760545449882,
          "clarke_a": 45.13888888888889,
          "clarke_b": 50.69444444444444,
          "clarke_ab": 95.83333333333334,
          "day": 33,
          "days_since_retrain": 5
        },
        {
          "mae": 49.48281772534896,
          "rmse": 56.471451579163926,
          "mse": 3189.0248434578557,
          "mape": 27.94095796613536,
          "correlation": 0.9199614103180155,
          "r_squared": -22.030108307371766,
          "clarke_a": 31.40495867768595,
          "clarke_b": 56.611570247933884,
          "clarke_ab": 88.01652892561984,
          "day": 34,
          "days_since_retrain": 6
        },
        {
          "mae": 22.642773280757826,
          "rmse": 29.64094698421794,
          "mse": 878.5857381212186,
          "mape": 12.71833438711033,
          "correlation": 0.8273354441032703,
          "r_squared": -1.3311335105392348,
          "clarke_a": 87.84722222222221,
          "clarke_b": 10.416666666666668,
          "clarke_ab": 98.26388888888889,
          "day": 35,
          "days_since_retrain": 0
        },
        {
          "mae": 21.72046014374001,
          "rmse": 30.33470933525491,
          "mse": 920.1945904544015,
          "mape": 12.621247139716576,
          "correlation": 0.8779091347316297,
          "r_squared": -1.1314515274277999,
          "clarke_a": 78.47222222222221,
          "clarke_b": 21.52777777777778,
          "clarke_ab": 100.0,
          "day": 36,
          "days_since_retrain": 1
        },
        {
          "mae": 19.89360897663518,
          "rmse": 28.114023538443902,
          "mse": 790.3983195201779,
          "mape": 11.187611911888812,
          "correlation": 0.7587000478523616,
          "r_squared": -2.604015885259642,
          "clarke_a": 92.01388888888889,
          "clarke_b": 6.597222222222222,
          "clarke_ab": 98.61111111111111,
          "day": 37,
          "days_since_retrain": 2
        },
        {
          "mae": 32.38499938987521,
          "rmse": 38.19430069805796,
          "mse": 1458.8046058136706,
          "mape": 17.353646884599815,
          "correlation": 0.8461939526884215,
          "r_squared": -1.3400546574046173,
          "clarke_a": 67.70833333333334,
          "clarke_b": 32.29166666666667,
          "clarke_ab": 100.00000000000001,
          "day": 38,
          "days_since_retrain": 3
        },
        {
          "mae": 19.753872294849273,
          "rmse": 25.31157497300774,
          "mse": 640.6758276141918,
          "mape": 11.739300029161853,
          "correlation": 0.7047949184513265,
          "r_squared": -2.549615977766492,
          "clarke_a": 85.41666666666666,
          "clarke_b": 12.847222222222221,
          "clarke_ab": 98.26388888888889,
          "day": 39,
          "days_since_retrain": 4
        },
        {
          "mae": 25.936039418838785,
          "rmse": 28.171400805718644,
          "mse": 793.627823356445,
          "mape": 15.937222292751677,
          "correlation": 0.8887880096774357,
          "r_squared": -3.423044759350943,
          "clarke_a": 66.13545816733067,
          "clarke_b": 33.86454183266932,
          "clarke_ab": 99.99999999999999,
          "day": 40,
          "days_since_retrain": 5
        },
        {
          "mae": 20.03259148312212,
          "rmse": 25.210033424852867,
          "mse": 635.5457852821988,
          "mape": 12.662676058698535,
          "correlation": 0.7522124644910243,
          "r_squared": -1.2505611713240534,
          "clarke_a": 71.52777777777779,
          "clarke_b": 28.47222222222222,
          "clarke_ab": 100.0,
          "day": 41,
          "days_since_retrain": 6
        },
        {
          "mae": 25.977261025646353,
          "rmse": 36.1903393334631,
          "mse": 1309.7406610712067,
          "mape": 16.58127028927018,
          "correlation": 0.6640394657195673,
          "r_squared": -2.555982280324182,
          "clarke_a": 72.22222222222221,
          "clarke_b": 25.0,
          "clarke_ab": 97.22222222222221,
          "day": 42,
          "days_since_retrain": 0
        },
        {
          "mae": 29.07974136303848,
          "rmse": 34.01553854786607,
          "mse": 1157.0568627013624,
          "mape": 18.685733708235183,
          "correlation": 0.6991470112846893,
          "r_squared": -7.0999912691552804,
          "clarke_a": 50.0,
          "clarke_b": 49.65277777777778,
          "clarke_ab": 99.65277777777777,
          "day": 43,
          "days_since_retrain": 1
        },
        {
          "mae": 38.079355142309154,
          "rmse": 43.980025828598436,
          "mse": 1934.2426718841853,
          "mape": 21.900095439809387,
          "correlation": 0.8322333741244724,
          "r_squared": -4.712736977833423,
          "clarke_a": 55.208333333333336,
          "clarke_b": 43.75,
          "clarke_ab": 98.95833333333334,
          "day": 44,
          "days_since_retrain": 2
        },
        {
          "mae": 21.829960808527915,
          "rmse": 26.649574355279476,
          "mse": 710.1998133175695,
          "mape": 13.480516458131312,
          "correlation": 0.6782648237079123,
          "r_squared": -4.385564641992565,
          "clarke_a": 78.57142857142857,
          "clarke_b": 20.714285714285715,
          "clarke_ab": 99.28571428571428,
          "day": 45,
          "days_since_retrain": 3
        }
      ],
      "retrain_events": [
        14,
        21,
        28,
        35,
        42
      ],
      "model": "lstm",
      "horizon_minutes": 30
    }
  }
}